Workbook

Sheet Dashboard
A1: DASHBOARD EJECUTIVO - COTIZACIÓN INTEGRAL
A2: Indicadores clave, desglose por categoría, utilidad y costo total final.
A4: COSTO DIRECTO TOTAL | D4: TOTAL CON UTILIDAD + IVA
A5: =Cotización!I21 | D5: =Cotización!I25
A8: Resumen de Inversión por Categoría
A10: Categoría del Proyecto | B10: Costo Total Directo (MXN) | C10: % del Costo Directo
A11: 1. Análisis y Diseño | B11: =SUMIF(Cotización!A$5:A$20, A11, Cotización!I$5:I$20) | C11: =B11/$B$19
A12: 2. Desarrollo Backend | B12: =SUMIF(Cotización!A$5:A$20, A12, Cotización!I$5:I$20) | C12: =B12/$B$19
A13: 3. Desarrollo Frontend | B13: =SUMIF(Cotización!A$5:A$20, A13, Cotización!I$5:I$20) | C13: =B13/$B$19
A14: 4. QA & Pruebas | B14: =SUMIF(Cotización!A$5:A$20, A14, Cotización!I$5:I$20) | C14: =B14/$B$19
A15: 5. Despliegue y DevOps | B15: =SUMIF(Cotización!A$5:A$20, A15, Cotización!I$5:I$20) | C15: =B15/$B$19
A16: 6. Gestión de Proyecto | B16: =SUMIF(Cotización!A$5:A$20, A16, Cotización!I$5:I$20) | C16: =B16/$B$19
A17: 7. Herramientas IA & Agentes | B17: =SUMIF(Cotización!A$5:A$20, A17, Cotización!I$5:I$20) | C17: =B17/$B$19
A18: 8. Infraestructura / Hosting | B18: =SUMIF(Cotización!A$5:A$20, A18, Cotización!I$5:I$20) | C18: =B18/$B$19
A19: COSTO DIRECTO TOTAL | B19: =SUM(B11:B18) | C19: =SUM(C11:C18)

Sheet Cotización
A1: COTIZACIÓN INTEGRAL DE PROYECTO DE DESARROLLO DE SOFTWARE
A2: Estimación con desglose de ingeniería (jornada de 40 hrs/sem: 8 hrs/día), herramientas IA, hosting y margen de utilidad.
A4: Fase / Categoría | B4: Descripción del Entregable / Concepto | C4: Rol / Recurso | D4: Horas Est. | E4: Semanas (40h) | F4: Días (8h) | G4: Meses (160h) | H4: Tarifa / Costo Unitario (MXN) | I4: Costo Total (MXN)
A5: 1. Análisis y Diseño | B5: Requerimientos, diagrama de arquitectura y flujos de usuario (UX/UI) | C5: Arquitecto de Software | D5: 35 | E5: =D5/40 | F5: =D5/8 | G5: =D5/160 | H5: 650 | I5: =D5*H5
A6: 1. Análisis y Diseño | B6: Diseño de base de datos y esquemas de seguridad | C6: DBA / Tech Lead | D6: 25 | E6: =D6/40 | F6: =D6/8 | G6: =D6/160 | H6: 600 | I6: =D6*H6
A7: 2. Desarrollo Backend | B7: Configuración de servidor, API REST y autenticación JWT | C7: Desarrollador Backend Sr | D7: 60 | E7: =D7/40 | F7: =D7/8 | G7: =D7/160 | H7: 500 | I7: =D7*H7
A8: 2. Desarrollo Backend | B8: Implementación de lógica de negocio y conectores | C8: Desarrollador Backend Jr | D8: 80 | E8: =D8/40 | F8: =D8/8 | G8: =D8/160 | H8: 350 | I8: =D8*H8
A9: 3. Desarrollo Frontend | B9: Maquetación de pantallas responsive y conexión con API | C9: Desarrollador Frontend Sr | D9: 60 | E9: =D9/40 | F9: =D9/8 | G9: =D9/160 | H9: 480 | I9: =D9*H9
A10: 3. Desarrollo Frontend | B10: Componentes de interfaz y validaciones de formularios | C10: Desarrollador Frontend Jr | D10: 70 | E10: =D10/40 | F10: =D10/8 | G10: =D10/160 | H10: 320 | I10: =D10*H10
A11: 4. QA & Pruebas | B11: Pruebas unitarias, de integración y reporte de bugs | C11: Ingeniero QA | D11: 45 | E11: =D11/40 | F11: =D11/8 | G11: =D11/160 | H11: 400 | I11: =D11*H11
A12: 5. Despliegue y DevOps | B12: Configuración de entorno en la nube, CI/CD y dominios | C12: DevOps Engineer | D12: 25 | E12: =D12/40 | F12: =D12/8 | G12: =D12/160 | H12: 550 | I12: =D12*H12
A13: 6. Gestión de Proyecto | B13: Seguimiento ágil (Scrum), reuniones con cliente y entregas | C13: Project Manager | D13: 30 | E13: =D13/40 | F13: =D13/8 | G13: =D13/160 | H13: 600 | I13: =D13*H13
A14: 7. Herramientas IA & Agentes | B14: Licenciamiento de Agentes de Desarrollo Autónomo (Cursor / Copilot Pro) | C14: Licencias / Mes | D14: 3 | E14: =D14/40 | F14: =D14/8 | G14: =D14/160 | H14: 450 | I14: =D14*H14
A15: 7. Herramientas IA & Agentes | B15: Consumo de API de LLMs (OpenAI / Anthropic para lógica inteligente y testing) | C15: Tokens / Consumo | D15: 1 | E15: =D15/40 | F15: =D15/8 | G15: =D15/160 | H15: 1800 | I15: =D15*H15
A16: 7. Herramientas IA & Agentes | B16: Plataforma de automatización RPA y asistentes inteligentes (UiPath / Bots) | C16: Suscripción Proyecto | D16: 1 | E16: =D16/40 | F16: =D16/8 | G16: =D16/160 | H16: 2500 | I16: =D16*H16
... A19: 8. Infraestructura / Hosting | B19: Entorno de Staging / Pruebas dedicado para validación del cliente | C19: Servidor Staging | D19: 2 | E19: =D19/40 | F19: =D19/8 | G19: =D19/160 | H19: 600 | I19: =D19*H19
C21: COSTO DIRECTO TOTAL: | D21: =SUM(D5:D13) | E21: =SUM(E5:E13) | F21: =SUM(F5:F13) | G21: =SUM(G5:G13) | I21: =SUM(I5:I19)
H22: Margen de Utilidad (25%): | I22: =I21*0.25
H23: SUBTOTAL CON UTILIDAD: | I23: =I21+I22
H24: IVA (16%): | I24: =I23*0.16
H25: TOTAL GENERAL COTIZACIÓN (MXN): | I25: =I23+I24

Sheet Cronograma y Fases
A1: CRONOGRAMA Y DISTRIBUCIÓN DE FASES
A2: Resumen de duración, entregables y asignación temporal por fase del proyecto.
A4: Fase | B4: Semana Inicio | C4: Semana Fin | D4: Duración (Semanas) | E4: Entregable Principal | F4: Estado
A5: 1. Análisis y Diseño | B5: 1 | C5: 2 | D5: =C5-B5+1 | E5: Documento de Arquitectura y Mockups UX/UI | F5: Completado
A6: 2. Desarrollo Backend | B6: 3 | C6: 6 | D6: =C6-B6+1 | E6: API REST funcional y Base de Datos Configurada | F6: En Progreso
A7: 3. Desarrollo Frontend | B7: 5 | C7: 8 | D7: =C7-B7+1 | E7: Interfaces de Usuario integradas con API | F7: Pendiente
A8: 4. QA & Pruebas | B8: 8 | C8: 9 | D8: =C8-B8+1 | E8: Reporte de Pruebas y Corrección de Bugs | F8: Pendiente
A9: 5. Despliegue y DevOps | B9: 10 | C9: 10 | D9: =C9-B9+1 | E9: Sistema en Producción y Manual de Usuario | F9: Pendiente
A10: 6. Gestión de Proyecto | B10: 1 | C10: 10 | D10: =C10-B10+1 | E10: Reportes de Avance y Actas de Entrega | F10: En Progreso
A11: 7. Herramientas IA & Agentes | B11: 1 | C11: 10 | D11: =C11-B11+1 | E11: Integración de Agentes y Automatización RPA | F11: En Progreso
A12: 8. Infraestructura / Hosting | B12: 9 | C12: 10 | D12: =C12-B12+1 | E12: Servidores Cloud y Certificados SSL Configurados | F12: Pendiente
